catrxneng/__init__.py
catrxneng/conf/FR100.py
catrxneng/conf/FR300.py
catrxneng/conf/__init__.py
catrxneng/conf/co2_fts.py
catrxneng/conf/co2_fts_data_conf.py
catrxneng/kinetic_models/__init__.py
catrxneng/kinetic_models/composite_kinetic_model.py
catrxneng/kinetic_models/kinetic_model.py
catrxneng/kinetic_models/reverse_kinetic_model.py
catrxneng/kinetic_models/co2_fts/__init__.py
catrxneng/kinetic_models/co2_fts/brubach2022.py
catrxneng/kinetic_models/co2_to_c1/__init__.py
catrxneng/kinetic_models/co2_to_c1/co2_to_meoh_with_dehydration.py
catrxneng/kinetic_models/co2_to_c1/ghosh2021.py
catrxneng/kinetic_models/co2_to_c1/ghosh2021_no_h2_in_denom.py
catrxneng/kinetic_models/co2_to_c1/ghosh2021_no_h2_in_denom_rev.py
catrxneng/kinetic_models/co2_to_c1/ghosh2021_without_sabatier.py
catrxneng/kinetic_models/co2_to_c1/power_law.py
catrxneng/kinetic_models/co2_to_c1/power_law_cza_sim.py
catrxneng/kinetic_models/co2_to_c1/power_law_only_meoh.py
catrxneng/kinetic_models/co2_to_c1/simple_LH.py
catrxneng/kinetic_models/co_hydrogenation/__init__.py
catrxneng/kinetic_models/co_hydrogenation/co_hydrogenation.py
catrxneng/kinetic_models/co_hydrogenation/co_to_meoh_with_dehydration.py
catrxneng/kinetic_models/mto/__init__.py
catrxneng/kinetic_models/mto/ghosh2022.py
catrxneng/kinetic_models/mto/ghosh2022_simplified.py
catrxneng/kinetic_models/mto/lee2019.py
catrxneng/kinetic_models/mto/mto_kinetic_model.py
catrxneng/kinetic_models/tandem/__init__.py
catrxneng/kinetic_models/tandem/ghosh2022_composite.py
catrxneng/kinetic_models/tandem/ghosh2022_full.py
catrxneng/kinetic_models/tandem/ghosh_ghoshmod.py
catrxneng/kinetic_models/tandem/ghosh_lee.py
catrxneng/kinetic_models/tandem/power_law_Ghosh2022_simplified.py
catrxneng/material/__init__.py
catrxneng/material/catalyst.py
catrxneng/material/cza_catalyst.py
catrxneng/material/material.py
catrxneng/phases/__init__.py
catrxneng/phases/gas_mixture.py
catrxneng/plots/__init__.py
catrxneng/plots/basic_plot.py
catrxneng-1.20260118.2.dist-info/METADATA
catrxneng-1.20260118.2.dist-info/WHEEL
catrxneng-1.20260118.2.dist-info/top_level.txt
catrxneng-1.20260118.2.dist-info/RECORD
