Metadata-Version: 2.4
Name: catrxneng
Version: 1.20260118.2
Summary: A collection of Python utilities for catalysis and reaction engineering.
Author: Gordon Brezicki
Project-URL: Homepage, https://github.com/gpbrez/catrxneng
Classifier: Programming Language :: Python :: 3
Classifier: License :: OSI Approved :: MIT License
Requires-Dist: numpy
Requires-Dist: scipy
Requires-Dist: pandas
Requires-Dist: influxdb-client
Requires-Dist: plotly
Requires-Dist: requests
